LICENSE
MANIFEST.in
README.md
pyproject.toml
requirements.txt
setup.cfg
setup.py
trackerhub/__init__.py
trackerhub/tracker_zoo.py
trackerhub.egg-info/PKG-INFO
trackerhub.egg-info/SOURCES.txt
trackerhub.egg-info/dependency_links.txt
trackerhub.egg-info/requires.txt
trackerhub.egg-info/top_level.txt
trackerhub/configs/__init__.py
trackerhub/configs/yolov6/__init__.py
trackerhub/utils/__init__.py
trackerhub/utils/config_utils.py
trackerhub/utils/dataset.py
trackerhub/utils/file_utils.py
trackerhub/utils/track_vis.py
trackerhub/utils/video_utils.py