Metadata-Version: 2.1
Name: trackerhub
Version: 0.0.3
Summary: Real-time Multi-Object Tracking Library
Home-page: https://github.com/kadirnar/trackerhub
Author: kadirnar
License: MIT
Keywords: deep-learning,vision,object-tracker,object-detection,yolov7,detector,yolov5,tracker,strongsort,bytetack,ocsort,norfair
Classifier: Development Status :: 5 - Production/Stable
Classifier: Operating System :: OS Independent
Classifier: Intended Audience :: Developers
Classifier: Intended Audience :: Science/Research
Classifier: Programming Language :: Python :: 3
Classifier: Programming Language :: Python :: 3.7
Classifier: Programming Language :: Python :: 3.8
Classifier: Programming Language :: Python :: 3.9
Classifier: Topic :: Software Development :: Libraries
Classifier: Topic :: Software Development :: Libraries :: Python Modules
Classifier: Topic :: Education
Classifier: Topic :: Scientific/Engineering
Classifier: Topic :: Scientific/Engineering :: Artificial Intelligence
Requires-Python: >=3.7
License-File: LICENSE
